trades_importer/__init__.py
trades_importer/simplywallst.py
trades_importer/wallmine.py
trades_importer-1.0.1.dist-info/METADATA
trades_importer-1.0.1.dist-info/WHEEL
trades_importer-1.0.1.dist-info/top_level.txt
trades_importer-1.0.1.dist-info/RECORD
