Metadata-Version: 2.1
Name: trades-importer
Version: 1.0.1
Summary: UNKNOWN
Home-page: UNKNOWN
Author: Cosmin Catalin Sanda
Author-email: cosmincatalin@gmail.com
License: UNKNOWN
Platform: UNKNOWN
Classifier: Programming Language :: Python :: 3
Classifier: Programming Language :: Python :: 3.8
Requires-Dist: requests (>=2)
Requires-Dist: beautifulsoup4 (>=4)
